Workbook

Sheet Facture
A1: FACTURE
A2: Nourix Academy · Projet 2 · Choisissez un code produit dans la liste et la quantité : le reste est automatique.
A4: Entreprise : | B4: Librairie Exemple
A5: Adresse : | B5: 12, rue Exemple, Ville
A6: Client : | B6: Client Exemple
A7: N° facture : | B7: F-2026-0042
A8: Date : | B8: 46300
A10: Code | B10: Désignation | C10: Prix unitaire HT | D10: Quantité | E10: Total HT | F10: Unité
A11: P001 | B11: =IF(A11="","",IFERROR(VLOOKUP(A11,Produits!$A$5:$D$100,2,FALSE()),"Code inconnu")) -> Cahier 96 pages | C11: =IF(A11="","",IFERROR(VLOOKUP(A11,Produits!$A$5:$D$100,3,FALSE()),0)) -> 120 | D11: 10 | E11: =IF(OR(A11="",D11=""),"",C11*D11) -> 1200 | F11: =IF(A11="","",IFERROR(VLOOKUP(A11,Produits!$A$5:$D$100,4,FALSE()),"")) -> pièce
A12: P002 | B12: =IF(A12="","",IFERROR(VLOOKUP(A12,Produits!$A$5:$D$100,2,FALSE()),"Code inconnu")) -> Stylo bleu | C12: =IF(A12="","",IFERROR(VLOOKUP(A12,Produits!$A$5:$D$100,3,FALSE()),0)) -> 30 | D12: 25 | E12: =IF(OR(A12="",D12=""),"",C12*D12) -> 750 | F12: =IF(A12="","",IFERROR(VLOOKUP(A12,Produits!$A$5:$D$100,4,FALSE()),"")) -> pièce
A13: P004 | B13: =IF(A13="","",IFERROR(VLOOKUP(A13,Produits!$A$5:$D$100,2,FALSE()),"Code inconnu")) -> Ramette papier A4 | C13: =IF(A13="","",IFERROR(VLOOKUP(A13,Produits!$A$5:$D$100,3,FALSE()),0)) -> 750 | D13: 2 | E13: =IF(OR(A13="",D13=""),"",C13*D13) -> 1500 | F13: =IF(A13="","",IFERROR(VLOOKUP(A13,Produits!$A$5:$D$100,4,FALSE()),"")) -> paquet
A14: P006 | B14: =IF(A14="","",IFERROR(VLOOKUP(A14,Produits!$A$5:$D$100,2,FALSE()),"Code inconnu")) -> Calculatrice | C14: =IF(A14="","",IFERROR(VLOOKUP(A14,Produits!$A$5:$D$100,3,FALSE()),0)) -> 1200 | D14: 1 | E14: =IF(OR(A14="",D14=""),"",C14*D14) -> 1200 | F14: =IF(A14="","",IFERROR(VLOOKUP(A14,Produits!$A$5:$D$100,4,FALSE()),"")) -> pièce
B15: =IF(A15="","",IFERROR(VLOOKUP(A15,Produits!$A$5:$D$100,2,FALSE()),"Code inconnu")) | C15: =IF(A15="","",IFERROR(VLOOKUP(A15,Produits!$A$5:$D$100,3,FALSE()),0)) | E15: =IF(OR(A15="",D15=""),"",C15*D15) | F15: =IF(A15="","",IFERROR(VLOOKUP(A15,Produits!$A$5:$D$100,4,FALSE()),""))
B16: =IF(A16="","",IFERROR(VLOOKUP(A16,Produits!$A$5:$D$100,2,FALSE()),"Code inconnu")) | C16: =IF(A16="","",IFERROR(VLOOKUP(A16,Produits!$A$5:$D$100,3,FALSE()),0)) | E16: =IF(OR(A16="",D16=""),"",C16*D16) | F16: =IF(A16="","",IFERROR(VLOOKUP(A16,Produits!$A$5:$D$100,4,FALSE()),""))
B17: =IF(A17="","",IFERROR(VLOOKUP(A17,Produits!$A$5:$D$100,2,FALSE()),"Code inconnu")) | C17: =IF(A17="","",IFERROR(VLOOKUP(A17,Produits!$A$5:$D$100,3,FALSE()),0)) | E17: =IF(OR(A17="",D17=""),"",C17*D17) | F17: =IF(A17="","",IFERROR(VLOOKUP(A17,Produits!$A$5:$D$100,4,FALSE()),""))
B18: =IF(A18="","",IFERROR(VLOOKUP(A18,Produits!$A$5:$D$100,2,FALSE()),"Code inconnu")) | C18: =IF(A18="","",IFERROR(VLOOKUP(A18,Produits!$A$5:$D$100,3,FALSE()),0)) | E18: =IF(OR(A18="",D18=""),"",C18*D18) | F18: =IF(A18="","",IFERROR(VLOOKUP(A18,Produits!$A$5:$D$100,4,FALSE()),""))
D20: Sous-total HT | E20: =SUM(E11:E18) -> 4650
D21: Remise | E21: 0.05
D22: Montant de la remise | E22: =E20*E21 -> 232.5
D23: Taux de TVA | E23: 0.19 | F23: Adaptez au taux de votre pays
D24: TVA | E24: =ROUND((E20-E22)*E23,2) -> 839.33
D25: TOTAL TTC | E25: =E20-E22+E24 -> 5256.83
A27: Arrêtée la présente facture à la somme indiquée ci-dessus. Merci de votre confiance.
A29: Légende : | B29: Saisie (modifiable) | C29: Formule (ne pas modifier)

Sheet Produits
A1: Catalogue des produits
A2: Ajoutez vos produits ici : la facture les retrouve par leur code.
A4: Code | B4: Désignation | C4: Prix unitaire HT | D4: Unité
A5: P001 | B5: Cahier 96 pages | C5: 120 | D5: pièce
A6: P002 | B6: Stylo bleu | C6: 30 | D6: pièce
A7: P003 | B7: Classeur A4 | C7: 250 | D7: pièce
A8: P004 | B8: Ramette papier A4 | C8: 750 | D8: paquet
A9: P005 | B9: Agenda 2027 | C9: 400 | D9: pièce
A10: P006 | B10: Calculatrice | C10: 1200 | D10: pièce
A11: P007 | B11: Trousse | C11: 350 | D11: pièce
A12: P008 | B12: Clé USB 32 Go | C12: 900 | D12: pièce
A13: P009 | B13: Surligneurs (x4) | C13: 280 | D13: lot
A14: P010 | B14: Cartable | C14: 2500 | D14: pièce
